siwar/__init__.py
siwar/client.py
siwar/constants.py
siwar/exceptions.py
siwar/utils.py
siwar/models/__init__.py
siwar/models/core.py
siwar/models/enums.py
siwar_api-0.1.0.dist-info/LICENSE
siwar_api-0.1.0.dist-info/METADATA
siwar_api-0.1.0.dist-info/WHEEL
siwar_api-0.1.0.dist-info/top_level.txt
siwar_api-0.1.0.dist-info/RECORD
