Metadata-Version: 2.1
Name: siwar-api
Version: 0.1.0
Summary: Python wrapper for the Siwar Arabic Lexicon API
Author-email: Osama Ata <osama.ata@outlook.com>
License: MIT
Project-URL: Homepage, https://github.com/osama-ata/siwar-api
Project-URL: Repository, https://github.com/osama-ata/siwar-api.git
Project-URL: Bug Tracker, https://github.com/osama-ata/siwar-api/issues
Keywords: arabic,dictionary,lexicon,nlp,language
Classifier: Development Status :: 4 - Beta
Classifier: Intended Audience :: Developers
Classifier: License :: OSI Approved :: MIT License
Classifier: Operating System :: OS Independent
Classifier: Programming Language :: Python :: 3
Classifier: Programming Language :: Python :: 3.10
Classifier: Programming Language :: Python :: 3.11
Classifier: Topic :: Software Development :: Libraries :: Python Modules
Classifier: Topic :: Text Processing :: Linguistic
Requires-Python: >=3.10
License-File: LICENSE
Requires-Dist: requests>=2.25.0
Requires-Dist: python-dateutil>=2.8.2
Provides-Extra: dev
Requires-Dist: pytest>=7.0.0; extra == "dev"
Requires-Dist: pytest-cov>=3.0.0; extra == "dev"
Requires-Dist: mypy>=1.0.0; extra == "dev"
Requires-Dist: flake8>=3.9.0; extra == "dev"
Requires-Dist: black>=22.0.0; extra == "dev"
Requires-Dist: isort>=5.9.0; extra == "dev"
Requires-Dist: types-requests>=2.25.0; extra == "dev"
Requires-Dist: responses>=0.23.0; extra == "dev"
